http_status_checker_tool-1.0.5.dist-info/licenses/LICENSE
status_checker/__init__.py
status_checker/cli.py
status_checker/core.py
status_checker/utils.py
status_checker/__pycache__/__init__.cpython-311.pyc
status_checker/__pycache__/cli.cpython-311.pyc
status_checker/__pycache__/core.cpython-311.pyc
http_status_checker_tool-1.0.5.dist-info/METADATA
http_status_checker_tool-1.0.5.dist-info/WHEEL
http_status_checker_tool-1.0.5.dist-info/entry_points.txt
http_status_checker_tool-1.0.5.dist-info/top_level.txt
http_status_checker_tool-1.0.5.dist-info/RECORD
