Metadata-Version: 2.4
Name: http-status-checker-tool
Version: 1.0.5
Summary: Basic - Fast, concurrent CLI tool to check HTTP status codes of provided URLs
Home-page: https://github.com/qazi112/http-status-checker
Author: Qazi Arsalan Shah
Project-URL: Source, https://github.com/qazi112/http-status-checker
Project-URL: Tracker, https://github.com/qazi112/http-status-checker/issues
Classifier: Programming Language :: Python :: 3
Classifier: Operating System :: OS Independent
Requires-Python: >=3.7
License-File: LICENSE
Requires-Dist: requests>=2.25.1
Requires-Dist: colorama>=0.4.6
Dynamic: author
Dynamic: classifier
Dynamic: description
Dynamic: description-content-type
Dynamic: home-page
Dynamic: license-file
Dynamic: project-url
Dynamic: requires-dist
Dynamic: requires-python
Dynamic: summary
